{
  "id": "1908:237",
  "type": "statute",
  "title": "Bekendtgørelse om en mellem Danmark og Portugal afsluttet Konvention angaaende obligatorisk Voldgift. (* 1)",
  "short_name": "Bekendtgørelse (international)",
  "status": "in_force",
  "issued_date": "1908-10-29",
  "url": "https://www.retsinformation.dk/eli/lta/1908/237/xml",
  "description": "Retsinformation source. DocumentId=CM029369; AccessionNumber=L19080023764; Characters preserved in NFC; ASCII fallback used only for key/file generation.",
  "provisions": [],
  "provision_versions": [],
  "definitions": []
}
