{
  "id": "1908:274",
  "type": "statute",
  "title": "Lov om Forældelse af visse Fordringer. (* 1) (1908Loven) (1908-Loven)",
  "short_name": "Lov",
  "status": "in_force",
  "issued_date": "1908-12-22",
  "url": "https://www.retsinformation.dk/eli/lta/1908/274/xml",
  "description": "Retsinformation source. DocumentId=CM018319; AccessionNumber=A19080027430; Characters preserved in NFC; ASCII fallback used only for key/file generation.",
  "provisions": [],
  "provision_versions": [],
  "definitions": []
}
