{
  "id": "1956:215",
  "type": "statute",
  "title": "Bekendtgørelse om anvendelse af æg i levnedsmidler m.m.",
  "short_name": "Bekendtgørelse",
  "status": "in_force",
  "issued_date": "1956-07-23",
  "url": "https://www.retsinformation.dk/eli/lta/1956/215/xml",
  "description": "Retsinformation source. DocumentId=CM044185; AccessionNumber=B19560021505; Characters preserved in NFC; ASCII fallback used only for key/file generation.",
  "provisions": [],
  "provision_versions": [],
  "definitions": []
}
