{
  "id": "1974:261",
  "type": "statute",
  "title": "Bekendtgørelse om ændring af bekendtgørelse om visse byggeforeningers frigørelse for tilskudsbestemmelser",
  "short_name": "Ændringsbekendtgørelse",
  "status": "in_force",
  "issued_date": "1974-05-20",
  "url": "https://www.retsinformation.dk/eli/lta/1974/261/xml",
  "description": "Retsinformation source. DocumentId=AO003138; AccessionNumber=B19740026105; Characters preserved in NFC; ASCII fallback used only for key/file generation.",
  "provisions": [],
  "provision_versions": [],
  "definitions": []
}
