{
  "id": "1975:492",
  "type": "statute",
  "title": "Bekendtgørelse om ændringer i ministeriernes forretningsområder\\n(Sager vedrørende loven om farten på Gudenå mellem Silkeborg og Randers)",
  "short_name": "Bekendtgørelse",
  "status": "in_force",
  "issued_date": "1975-09-15",
  "url": "https://www.retsinformation.dk/eli/lta/1975/492/xml",
  "description": "Retsinformation source. DocumentId=AP000161; AccessionNumber=B19750049205; Characters preserved in NFC; ASCII fallback used only for key/file generation.",
  "provisions": [],
  "provision_versions": [],
  "definitions": []
}
