{
  "id": "1976:95",
  "type": "statute",
  "title": "Bekendtgørelse om svangerskabsafbrydelse. (Fremsættelse af anmodning m.v.)",
  "short_name": "Bekendtgørelse",
  "status": "in_force",
  "issued_date": "1976-03-10",
  "url": "https://www.retsinformation.dk/eli/lta/1976/95/xml",
  "description": "Retsinformation source. DocumentId=CM016319; AccessionNumber=B19760009505; Characters preserved in NFC; ASCII fallback used only for key/file generation.",
  "provisions": [],
  "provision_versions": [],
  "definitions": []
}
