{
  "id": "1978:366",
  "type": "statute",
  "title": "Bekendtgørelse om ydelse af støtte til tørret foder",
  "short_name": "Bekendtgørelse",
  "status": "in_force",
  "issued_date": "1978-07-17",
  "url": "https://www.retsinformation.dk/eli/lta/1978/366/xml",
  "description": "Retsinformation source. DocumentId=CM036679; AccessionNumber=B19780036605; Characters preserved in NFC; ASCII fallback used only for key/file generation.",
  "provisions": [],
  "provision_versions": [],
  "definitions": []
}
