{
  "id": "1982:350",
  "type": "statute",
  "title": "Bekendtgørelse om tilskud for opretholdelse eller forøgelse af antallet af lære- pg praktikpladser m.v. (* 1)",
  "short_name": "Bekendtgørelse",
  "status": "in_force",
  "issued_date": "1982-06-25",
  "url": "https://www.retsinformation.dk/eli/lta/1982/350/xml",
  "description": "Retsinformation source. DocumentId=CM032455; AccessionNumber=B19820035005; Characters preserved in NFC; ASCII fallback used only for key/file generation.",
  "provisions": [],
  "provision_versions": [],
  "definitions": []
}
