{
  "id": "1983:417",
  "type": "statute",
  "title": "Bekendtgørelse om skattemæssig kontrol med renteindtægter i pengeinstitutter m.v. og med obligationsrenter",
  "short_name": "Bekendtgørelse",
  "status": "in_force",
  "issued_date": "1983-08-30",
  "url": "https://www.retsinformation.dk/eli/lta/1983/417/xml",
  "description": "Retsinformation source. DocumentId=CM020187; AccessionNumber=B19830041705; Characters preserved in NFC; ASCII fallback used only for key/file generation.",
  "provisions": [],
  "provision_versions": [],
  "definitions": []
}
