{
  "id": "1984:231",
  "type": "statute",
  "title": "Lov om ændring af kildeskatteloven og skattestyrelsesloven (Fremrykket årsopgørelse m.v.)",
  "short_name": "Ændringslov",
  "status": "in_force",
  "issued_date": "1984-05-23",
  "url": "https://www.retsinformation.dk/eli/lta/1984/231/xml",
  "description": "Retsinformation source. DocumentId=CM022403; AccessionNumber=A19840023130; Characters preserved in NFC; ASCII fallback used only for key/file generation.",
  "provisions": [],
  "provision_versions": [],
  "definitions": []
}
