{
  "id": "1984:394",
  "type": "statute",
  "title": "Bekendtgørelse om udledning i havet af stoffer og materialer fra visse havanlæg",
  "short_name": "Bekendtgørelse",
  "status": "in_force",
  "issued_date": "1984-07-17",
  "url": "https://www.retsinformation.dk/eli/lta/1984/394/xml",
  "description": "Retsinformation source. DocumentId=CM007175; AccessionNumber=B19840039405; Characters preserved in NFC; ASCII fallback used only for key/file generation.",
  "provisions": [],
  "provision_versions": [],
  "definitions": []
}
