{
  "id": "1985:597",
  "type": "statute",
  "title": "Bekendtgørelse om forlængelse af den for Det Store Nordiske Telegraf-Selskab A/S udfærdigede koncession på anlæg og drift af et telekommunikationskabel mellem Island og Grønland og - i samarbejde med Canadian Overseas Telecommunication Corporation - mellem Grønland og Canada (ICECAN)",
  "short_name": "Bekendtgørelse",
  "status": "in_force",
  "issued_date": "1985-12-12",
  "url": "https://www.retsinformation.dk/eli/lta/1985/597/xml",
  "description": "Retsinformation source. DocumentId=CM003385; AccessionNumber=B19850059705; Characters preserved in NFC; ASCII fallback used only for key/file generation.",
  "provisions": [],
  "provision_versions": [],
  "definitions": []
}
