{
  "id": "1986:233",
  "type": "statute",
  "title": "Bekendtgørelse om beskyttelsesudstyr og gas-førstehjælpsudstyr i visse fiskefartøjer",
  "short_name": "Bekendtgørelse",
  "status": "in_force",
  "issued_date": "1986-05-09",
  "url": "https://www.retsinformation.dk/eli/lta/1986/233/xml",
  "description": "Retsinformation source. DocumentId=CM023482; AccessionNumber=B19860023305; Characters preserved in NFC; ASCII fallback used only for key/file generation.",
  "provisions": [],
  "provision_versions": [],
  "definitions": []
}
