{
  "id": "1987:552",
  "type": "statute",
  "title": "Bekendtgørelse om godkendelse af frikommuneregulativ nr. 7 for Herlev Kommune om fritagelse af en vis indtægt fra fradrag for arbejdsindtægter ved udbetaling af kontanthjælp",
  "short_name": "Bekendtgørelse",
  "status": "in_force",
  "issued_date": "1987-08-19",
  "url": "https://www.retsinformation.dk/eli/lta/1987/552/xml",
  "description": "Retsinformation source. DocumentId=CM012069; AccessionNumber=B19870055205; Characters preserved in NFC; ASCII fallback used only for key/file generation.",
  "provisions": [],
  "provision_versions": [],
  "definitions": []
}
