{
  "id": "1987:201",
  "type": "statute",
  "title": "Bekendtgørelse om formen for de af lærlingeloven omfattede svendebreve og lærebreve m.v.",
  "short_name": "Bekendtgørelse",
  "status": "in_force",
  "issued_date": "1987-04-10",
  "url": "https://www.retsinformation.dk/eli/lta/1987/201/xml",
  "description": "Retsinformation source. DocumentId=CM032279; AccessionNumber=B19870020105; Characters preserved in NFC; ASCII fallback used only for key/file generation.",
  "provisions": [],
  "provision_versions": [],
  "definitions": []
}
