{
  "id": "1988:298",
  "type": "statute",
  "title": "Bekendtgørelse om indvinding af sømaterialer i Samsø Bælt, Sejerø Bugt, Storebælt, Langelandsbælt og Smålandsfarvandet til Storebæltsforbindelsen",
  "short_name": "Bekendtgørelse",
  "status": "in_force",
  "issued_date": "1988-06-08",
  "url": "https://www.retsinformation.dk/eli/lta/1988/298/xml",
  "description": "Retsinformation source. DocumentId=CM007087; AccessionNumber=B19880029805; Characters preserved in NFC; ASCII fallback used only for key/file generation.",
  "provisions": [],
  "provision_versions": [],
  "definitions": []
}
