{
  "id": "1988:394",
  "type": "statute",
  "title": "Bekendtgørelse om folke- og førtidspensionens størrelse pr. 1. juli 1988 og delpensionens basisbeløb pr. 1. juli 1988",
  "short_name": "Bekendtgørelse",
  "status": "in_force",
  "issued_date": "1988-07-05",
  "url": "https://www.retsinformation.dk/eli/lta/1988/394/xml",
  "description": "Retsinformation source. DocumentId=CM012007; AccessionNumber=B19880039405; Characters preserved in NFC; ASCII fallback used only for key/file generation.",
  "provisions": [],
  "provision_versions": [],
  "definitions": []
}
