{
  "id": "1988:674",
  "type": "statute",
  "title": "Bekendtgørelse af lov om tilskud til vikarordninger inden for jordbruget",
  "short_name": "Lovbekendtgørelse",
  "status": "in_force",
  "issued_date": "1988-10-26",
  "url": "https://www.retsinformation.dk/eli/lta/1988/674/xml",
  "description": "Retsinformation source. DocumentId=CM038855; AccessionNumber=A19880067429; Characters preserved in NFC; ASCII fallback used only for key/file generation.",
  "provisions": [],
  "provision_versions": [],
  "definitions": []
}
