{
  "id": "1988:47",
  "type": "statute",
  "title": "Bekendtgørelse om værdiansættelsen af aktiver til dækning af reserven for løbende ydelser efter arbejdsskadeforsikringsloven",
  "short_name": "Bekendtgørelse",
  "status": "in_force",
  "issued_date": "1988-01-28",
  "url": "https://www.retsinformation.dk/eli/lta/1988/47/xml",
  "description": "Retsinformation source. DocumentId=CM023239; AccessionNumber=B19880004705; Characters preserved in NFC; ASCII fallback used only for key/file generation.",
  "provisions": [],
  "provision_versions": [],
  "definitions": []
}
