{
  "id": "1989:462",
  "type": "statute",
  "title": "Bekendtgørelse om produktionsafgifter på fjerkræ og æg",
  "short_name": "Bekendtgørelse",
  "status": "in_force",
  "issued_date": "1989-06-27",
  "url": "https://www.retsinformation.dk/eli/lta/1989/462/xml",
  "description": "Retsinformation source. DocumentId=CM036837; AccessionNumber=B19890046205; Characters preserved in NFC; ASCII fallback used only for key/file generation.",
  "provisions": [],
  "provision_versions": [],
  "definitions": []
}
