{
  "id": "1989:579",
  "type": "statute",
  "title": "Bekendtgørelse om ændring af bekendtgørelse om bekæmpelse af smitsomme sygdomme hos ferskvandsfisk",
  "short_name": "Ændringsbekendtgørelse",
  "status": "in_force",
  "issued_date": "1989-08-29",
  "url": "https://www.retsinformation.dk/eli/lta/1989/579/xml",
  "description": "Retsinformation source. DocumentId=CM037035; AccessionNumber=B19890057905; Characters preserved in NFC; ASCII fallback used only for key/file generation.",
  "provisions": [],
  "provision_versions": [],
  "definitions": []
}
