{
  "id": "1991:525",
  "type": "statute",
  "title": "Bekendtgørelse om ændring af bekendtgørelse om uddannelsesstøtte(* 1)",
  "short_name": "Ændringsbekendtgørelse",
  "status": "in_force",
  "issued_date": "1991-07-02",
  "url": "https://www.retsinformation.dk/eli/lta/1991/525/xml",
  "description": "Retsinformation source. DocumentId=CM032677; AccessionNumber=B19910052505; Characters preserved in NFC; ASCII fallback used only for key/file generation.",
  "provisions": [],
  "provision_versions": [],
  "definitions": []
}
