{
  "id": "1992:1004",
  "type": "statute",
  "title": "Lov om ændring af sømandsloven og om ophævelse af lov om mønstring af søfarende m.v. (* 1)",
  "short_name": "Ændringslov",
  "status": "in_force",
  "issued_date": "1992-12-19",
  "url": "https://www.retsinformation.dk/eli/lta/1992/1004/xml",
  "description": "Retsinformation source. DocumentId=CM025585; AccessionNumber=A19920100430; Characters preserved in NFC; ASCII fallback used only for key/file generation.",
  "provisions": [],
  "provision_versions": [],
  "definitions": []
}
