{
  "id": "1993:521",
  "type": "statute",
  "title": "Bekendtgørelse om ændring af bekendtgørelse om udbetaling af forskud og acontorefusion til de anerkendte arbejdsløshedskasser",
  "short_name": "Ændringsbekendtgørelse",
  "status": "in_force",
  "issued_date": "1993-06-30",
  "url": "https://www.retsinformation.dk/eli/lta/1993/521/xml",
  "description": "Retsinformation source. DocumentId=CM026559; AccessionNumber=B19930052105; Characters preserved in NFC; ASCII fallback used only for key/file generation.",
  "provisions": [],
  "provision_versions": [],
  "definitions": []
}
