{
  "id": "1993:843",
  "type": "statute",
  "title": "Bekendtgørelse om medlems- og dagpengeret for personer, der har haft arbejde eller ophold på Færøerne",
  "short_name": "Bekendtgørelse",
  "status": "in_force",
  "issued_date": "1993-10-22",
  "url": "https://www.retsinformation.dk/eli/lta/1993/843/xml",
  "description": "Retsinformation source. DocumentId=CM026767; AccessionNumber=B19930084305; Characters preserved in NFC; ASCII fallback used only for key/file generation.",
  "provisions": [],
  "provision_versions": [],
  "definitions": []
}
