{
  "id": "1995:239",
  "type": "statute",
  "title": "Bekendtgørelse om ansøgning og registrering af varemærker og fællesmærker (Ansøgningsbekendtgørelsen)",
  "short_name": "Bekendtgørelse",
  "status": "in_force",
  "issued_date": "1995-04-05",
  "url": "https://www.retsinformation.dk/eli/lta/1995/239/xml",
  "description": "Retsinformation source. DocumentId=CM023487; AccessionNumber=B19950023905; Characters preserved in NFC; ASCII fallback used only for key/file generation.",
  "provisions": [],
  "provision_versions": [],
  "definitions": []
}
