{
  "id": "1995:933",
  "type": "statute",
  "title": "Bekendtgørelse om ændring af bekendtgørelse om mælkeprodukter m.v.",
  "short_name": "Ændringsbekendtgørelse",
  "status": "in_force",
  "issued_date": "1995-12-07",
  "url": "https://www.retsinformation.dk/eli/lta/1995/933/xml",
  "description": "Retsinformation source. DocumentId=CM037590; AccessionNumber=B19950093305; Characters preserved in NFC; ASCII fallback used only for key/file generation.",
  "provisions": [],
  "provision_versions": [],
  "definitions": []
}
