{
  "id": "1996:626",
  "type": "statute",
  "title": "Bekendtgørelse om ophævelse af bekendtgørelse om skiltning med pris for visse restaurationsvarer og bekendtgørelse om prisskiltning i frisørsaloner.",
  "short_name": "Bekendtgørelse",
  "status": "in_force",
  "issued_date": "1996-06-28",
  "url": "https://www.retsinformation.dk/eli/lta/1996/626/xml",
  "description": "Retsinformation source. DocumentId=CM041181; AccessionNumber=B19960062605; Characters preserved in NFC; ASCII fallback used only for key/file generation.",
  "provisions": [],
  "provision_versions": [],
  "definitions": []
}
