{
  "id": "1996:1027",
  "type": "statute",
  "title": "Bekendtgørelse om ophævelse af bekendtgørelse om klassificering m.v. af bekæmpelsesmidler (farlighed for bier)",
  "short_name": "Bekendtgørelse",
  "status": "in_force",
  "issued_date": "1996-12-03",
  "url": "https://www.retsinformation.dk/eli/lta/1996/1027/xml",
  "description": "Retsinformation source. DocumentId=CM042558; AccessionNumber=B19960102705; Characters preserved in NFC; ASCII fallback used only for key/file generation.",
  "provisions": [],
  "provision_versions": [],
  "definitions": []
}
