{
  "id": "1996:1003",
  "type": "statute",
  "title": "Bekendtgørelse om ikrafttrædelse af cabotageregler i lov om Dansk Internationalt Skibsregister",
  "short_name": "Ikrafttræd. bekendtgørelse",
  "status": "in_force",
  "issued_date": "1996-11-29",
  "url": "https://www.retsinformation.dk/eli/lta/1996/1003/xml",
  "description": "Retsinformation source. DocumentId=CM042403; AccessionNumber=B19960100305; Characters preserved in NFC; ASCII fallback used only for key/file generation.",
  "provisions": [],
  "provision_versions": [],
  "definitions": []
}
