{
  "id": "1997:1074",
  "type": "statute",
  "title": "Bekendtgørelse om godkendelse af ændring af vedtægt om advokaters pligter med hensyn til behandlingen af betroede midler",
  "short_name": "Bekendtgørelse",
  "status": "in_force",
  "issued_date": "1997-12-19",
  "url": "https://www.retsinformation.dk/eli/lta/1997/1074/xml",
  "description": "Retsinformation source. DocumentId=CM046041; AccessionNumber=B19970107405; Characters preserved in NFC; ASCII fallback used only for key/file generation.",
  "provisions": [],
  "provision_versions": [],
  "definitions": []
}
