{
  "id": "1998:683",
  "type": "statute",
  "title": "Bekendtgørelse om børneopsparings- og selvpensioneringskonti",
  "short_name": "Bekendtgørelse",
  "status": "in_force",
  "issued_date": "1998-09-18",
  "url": "https://www.retsinformation.dk/eli/lta/1998/683/xml",
  "description": "Retsinformation source. DocumentId=AN000087; AccessionNumber=B19980068305; Characters preserved in NFC; ASCII fallback used only for key/file generation.",
  "provisions": [],
  "provision_versions": [],
  "definitions": []
}
