{
  "id": "1998:553",
  "type": "statute",
  "title": "Bekendtgørelse om ændring af bekendtgørelse om registrering og syn af køretøjer m.v.",
  "short_name": "Ændringsbekendtgørelse",
  "status": "in_force",
  "issued_date": "1998-07-27",
  "url": "https://www.retsinformation.dk/eli/lta/1998/553/xml",
  "description": "Retsinformation source. DocumentId=CM047631; AccessionNumber=B19980055305; Characters preserved in NFC; ASCII fallback used only for key/file generation.",
  "provisions": [],
  "provision_versions": [],
  "definitions": []
}
