{
  "id": "1999:460",
  "type": "statute",
  "title": "Bekendtgørelse om støtteberettigede udgifter til bygningsfornyelse, støttebortfald m.v. efter lov om byfornyelse",
  "short_name": "Bekendtgørelse",
  "status": "in_force",
  "issued_date": "1999-06-14",
  "url": "https://www.retsinformation.dk/eli/lta/1999/460/xml",
  "description": "Retsinformation source. DocumentId=AC000101; AccessionNumber=B19990046005; Characters preserved in NFC; ASCII fallback used only for key/file generation.",
  "provisions": [],
  "provision_versions": [],
  "definitions": []
}
