{
  "id": "1999:841",
  "type": "statute",
  "title": "Bekendtgørelse om regulering af sats for vægtafgift af motorkøretøjer m.v.",
  "short_name": "Bekendtgørelse",
  "status": "in_force",
  "issued_date": "1999-11-15",
  "url": "https://www.retsinformation.dk/eli/lta/1999/841/xml",
  "description": "Retsinformation source. DocumentId=AN000669; AccessionNumber=B19990084105; Characters preserved in NFC; ASCII fallback used only for key/file generation.",
  "provisions": [],
  "provision_versions": [],
  "definitions": []
}
