{
  "id": "1999:520",
  "type": "statute",
  "title": "Bekendtgørelse om ikrafttræden af dele af fiskerilov",
  "short_name": "Bekendtgørelse",
  "status": "in_force",
  "issued_date": "1999-06-24",
  "url": "https://www.retsinformation.dk/eli/lta/1999/520/xml",
  "description": "Retsinformation source. DocumentId=AH000298; AccessionNumber=B19990052005; Characters preserved in NFC; ASCII fallback used only for key/file generation.",
  "provisions": [],
  "provision_versions": [],
  "definitions": []
}
