{
  "id": "1999:764",
  "type": "statute",
  "title": "Bekendtgørelse af lov om indkomstbeskatning af selvstændige erhvervsdrivende",
  "short_name": "Lovbekendtgørelse",
  "status": "in_force",
  "issued_date": "1999-10-04",
  "url": "https://www.retsinformation.dk/eli/lta/1999/764/xml",
  "description": "Retsinformation source. DocumentId=AN000541; AccessionNumber=A19990076429; Characters preserved in NFC; ASCII fallback used only for key/file generation.",
  "provisions": [],
  "provision_versions": [],
  "definitions": []
}
