{
  "id": "2001:435",
  "type": "statute",
  "title": "Bekendtgørelse om ændring af bekendtgørelse om salmonella i kvæg og svin m.m.",
  "short_name": "Ændringsbekendtgørelse",
  "status": "in_force",
  "issued_date": "2001-05-31",
  "url": "https://www.retsinformation.dk/eli/lta/2001/435/xml",
  "description": "Retsinformation source. DocumentId=AH000935; AccessionNumber=B20010043505; Characters preserved in NFC; ASCII fallback used only for key/file generation.",
  "provisions": [],
  "provision_versions": [],
  "definitions": []
}
