{
  "id": "2002:831",
  "type": "statute",
  "title": "Bekendtgørelse om godkendelse af udsætning i miljøet af genetisk modificerede organismer",
  "short_name": "Bekendtgørelse",
  "status": "in_force",
  "issued_date": "2002-10-03",
  "url": "https://www.retsinformation.dk/eli/lta/2002/831/xml",
  "description": "Retsinformation source. DocumentId=AL000869; AccessionNumber=B20020083105; Characters preserved in NFC; ASCII fallback used only for key/file generation.",
  "provisions": [],
  "provision_versions": [],
  "definitions": []
}
