{
  "id": "2003:630",
  "type": "statute",
  "title": "Bekendtgørelse om visse aspekter i forbindelse med tilrettelæggelsen af arbejdstiden på havanlæg",
  "short_name": "Bekendtgørelse",
  "status": "in_force",
  "issued_date": "2003-07-01",
  "url": "https://www.retsinformation.dk/eli/lta/2003/630/xml",
  "description": "Retsinformation source. DocumentId=AU001121; AccessionNumber=B20030063005; Characters preserved in NFC; ASCII fallback used only for key/file generation.",
  "provisions": [],
  "provision_versions": [],
  "definitions": []
}
