{
  "id": "2004:480",
  "type": "statute",
  "title": "Lov om ændring af lov om statens voksenuddannelsesstøtte (SVU) og lov om godtgørelse ved deltagelse i erhvervsrettet voksen- og efteruddannelse\\n(Udvidelse af adgangen til SVU)",
  "short_name": "Ændringslov",
  "status": "in_force",
  "issued_date": "2004-06-09",
  "url": "https://www.retsinformation.dk/eli/lta/2004/480/xml",
  "description": "Retsinformation source. DocumentId=AT001815; AccessionNumber=A20040048030; Characters preserved in NFC; ASCII fallback used only for key/file generation.",
  "provisions": [],
  "provision_versions": [],
  "definitions": []
}
