{
  "id": "2004:368",
  "type": "statute",
  "title": "Bekendtgørelse om god skik for investeringsforeninger og specialforeninger samt udenlandske investeringsinstitutter",
  "short_name": "Bekendtgørelse",
  "status": "in_force",
  "issued_date": "2004-05-17",
  "url": "https://www.retsinformation.dk/eli/lta/2004/368/xml",
  "description": "Retsinformation source. DocumentId=AU001617; AccessionNumber=B20040036805; Characters preserved in NFC; ASCII fallback used only for key/file generation.",
  "provisions": [],
  "provision_versions": [],
  "definitions": []
}
