{
  "id": "2004:1058",
  "type": "statute",
  "title": "Bekendtgørelse om uddannelse til forsyningsoperatør",
  "short_name": "Bekendtgørelse",
  "status": "in_force",
  "issued_date": "2004-11-02",
  "url": "https://www.retsinformation.dk/eli/lta/2004/1058/xml",
  "description": "Retsinformation source. DocumentId=AT001977; AccessionNumber=B20040105805; Characters preserved in NFC; ASCII fallback used only for key/file generation.",
  "provisions": [],
  "provision_versions": [],
  "definitions": []
}
