{
  "id": "2005:833",
  "type": "statute",
  "title": "Bekendtgørelse af lov om udlevering af lovovertrædere",
  "short_name": "Lovbekendtgørelse",
  "status": "in_force",
  "issued_date": "2005-08-25",
  "url": "https://www.retsinformation.dk/eli/lta/2005/833/xml",
  "description": "Retsinformation source. DocumentId=AA002996; AccessionNumber=A20050083329; Characters preserved in NFC; ASCII fallback used only for key/file generation.",
  "provisions": [],
  "provision_versions": [],
  "definitions": []
}
