{
  "id": "2005:119",
  "type": "statute",
  "title": "Bekendtgørelse om statsrefusion og tilskud, samt regnskabsaflæggelse og revision på Socialministeriets, Beskæftigelsesministeriets, Ministeriet for Flygtninge, Indvandrere og Integrations og Ministeriet for Familie- og Forbrugeranliggenders ressortområder",
  "short_name": "Bekendtgørelse",
  "status": "in_force",
  "issued_date": "2005-02-24",
  "url": "https://www.retsinformation.dk/eli/lta/2005/119/xml",
  "description": "Retsinformation source. DocumentId=AO002509; AccessionNumber=B20050011905; Characters preserved in NFC; ASCII fallback used only for key/file generation.",
  "provisions": [],
  "provision_versions": [],
  "definitions": []
}
