{
  "id": "2005:1047",
  "type": "statute",
  "title": "Bekendtgørelse af lov om anvendelse af Det Europæiske Fællesskabs forordning om toldmyndighedernes indgriben over for varer, der mistænkes for at krænke visse intellektuelle ejendomsrettigheder, og om de foranstaltninger, som skal træffes over for varer, der krænker sådanne rettigheder",
  "short_name": "Lovbekendtgørelse",
  "status": "in_force",
  "issued_date": "2005-10-20",
  "url": "https://www.retsinformation.dk/eli/lta/2005/1047/xml",
  "description": "Retsinformation source. DocumentId=AN004896; AccessionNumber=A20050104729; Characters preserved in NFC; ASCII fallback used only for key/file generation.",
  "provisions": [],
  "provision_versions": [],
  "definitions": []
}
