{
  "id": "2007:157",
  "type": "statute",
  "title": "Bekendtgørelse om ændring af bekendtgørelse om prøver inden for danskuddannelse til voksne udlændinge m.fl.\\n(Udvidelse af forsøgsbestemmelse)",
  "short_name": "Ændringsbekendtgørelse",
  "status": "in_force",
  "issued_date": "2007-02-21",
  "url": "https://www.retsinformation.dk/eli/lta/2007/157/xml",
  "description": "Retsinformation source. DocumentId=BC000397; AccessionNumber=B20070015705; Characters preserved in NFC; ASCII fallback used only for key/file generation.",
  "provisions": [],
  "provision_versions": [],
  "definitions": []
}
