{
  "id": "2007:1182",
  "type": "statute",
  "title": "Bekendtgørelse om isafgift af de varemængder, der ud- og indskibes i visse danske havne",
  "short_name": "BEK H#LOKDOK04",
  "status": "in_force",
  "issued_date": "2007-10-04",
  "url": "https://www.retsinformation.dk/eli/lta/2007/1182/xml",
  "description": "Retsinformation source. DocumentId=AG000331; AccessionNumber=B20070118205; Characters preserved in NFC; ASCII fallback used only for key/file generation.",
  "provisions": [
    {
      "provision_ref": "1",
      "section": "1",
      "content": "§ 1. Havne med en vanddybde på 5 m eller derover beliggende inden for Skagen skal betale en årlig afgift som bidrag til dækning af udgifterne ved driften af Statens Istjeneste ."
    },
    {
      "provision_ref": "2",
      "section": "2",
      "content": "§ 2. Isafgiften vil fra og med 1. januar 2008 være at udrede med følgende beløb : Asnæsværkets Havn padding-left: 0.15cm; padding-right: 0.15cm; padding-top: 0cm; padding-bottom: 0cm; border-left: 0.018cm solid #000000; border-top: 0.018cm solid #000000; border-bottom: 0.018cm solid #000000 187 Kr. 192.863,58 padding-left: 0.15cm; padding-right: 0.15cm; padding-top: 0cm; padding-bottom: 0cm; border-left: 0.018cm solid #000000; border-top: 0.018cm solid #000000; border-bottom: 0.018cm solid #000000 114 Nexø Havn padding-left: 0.15cm; padding-right: 0.15cm; padding-top: 0cm; padding-bottom: 0cm; border-left: 0.018cm solid #000000; border-top: 0.018cm solid #000000; border-bottom: 0.018cm solid #000000 161 Kr. 3.859,27 padding-left: 0.15cm; padding-right: 0.15cm; padding-top: 0cm; padding-bottom: 0cm; border: 0.018cm solid #000000 133 Assens Havn padding-left: 0.15cm; padding-right: 0.15cm; padding-top: 0cm; padding-bottom: 0cm; border-left: 0.018cm solid #000000; border-bottom: 0.018cm solid #000000 187 Kr. 16.967,47 padding-left: 0.15cm; padding-right: 0.15cm; padding-top: 0cm; padding-bottom: 0cm; border-left: 0.018cm solid #000000; border-bottom: 0.018cm solid #000000 114 Nordjyllandsværkets Havn padding-left: 0.15cm; padding-right: 0.15cm; padding-top: 0cm; padding-bottom: 0cm; border-left: 0.018cm solid #000000; border-bottom: 0.018cm solid #000000 161 Kr. 113.413,12 padding-left: 0.15cm; padding-right: 0.15cm; padding-top: 0cm; padding-bottom: 0cm; border-left: 0.018cm solid #000000; border-right: 0.018cm solid #000000; border-bottom: 0.018cm solid #000000 133 Avedøreværkets Havn padding-left: 0.15cm; padding-right: 0.15cm; padding-top: 0cm; padding-bottom: 0cm; border-left: 0.018cm solid #000000; border-bottom: 0.018cm solid #000000 187 Kr. 109.964,18 padding-left: 0.15cm; padding-right: 0.15cm; padding-top: 0cm; padding-bottom: 0cm; border-left: 0.018cm solid #000000; border-bottom: 0.018cm solid #000000 114 Nyborg Havn padding-left: 0.15cm; padding-right: 0.15cm; padding-top: 0cm; padding-bottom: 0cm; border-left: 0.018cm solid #000000; border-bottom: 0.018cm solid #000000 161 Kr. 59.763,20 padding-left: 0.15cm; padding-right: 0.15cm; padding-top: 0cm; padding-bottom: 0cm; border-left: 0.018cm solid #000000; border-right: 0.018cm solid #000000; border-bottom: 0.018cm solid #000000 133 Bandholm-Maribo Havn padding-left: 0.15cm; padding-right: 0.15cm; padding-top: 0cm; padding-bottom: 0cm; border-left: 0.018cm solid #000000; border-bottom: 0.018cm solid #000000 187 Kr. 19.163,26 padding-left: 0.15cm; padding-right: 0.15cm; padding-top: 0cm; padding-bottom: 0cm; border-left: 0.018cm solid #000000; border-bottom: 0.018cm solid #000000 114 Nykøbing F. Havn padding-left: 0.15cm; padding-right: 0.15cm; padding-top: 0cm; padding-bottom: 0cm; border-left: 0.018cm solid #000000; border-bottom: 0.018cm solid #000000 161 Kr. 31.168,02 padding-left: 0.15cm; padding-right: 0.15cm; padding-top: 0cm; padding-bottom: 0cm; border-left: 0.018cm solid #000000; border-right: 0.018cm solid #000000; border-bottom: 0.018cm solid #000000 133 Enstedværkets Havn padding-left: 0.15cm; padding-right: 0.15cm; padding-top: 0cm; padding-bottom: 0cm; border-left: 0.018cm solid #000000; border-bottom: 0.018cm solid #000000 187 Kr. 555.684,64 padding-left: 0.15cm; padding-right: 0.15cm; padding-top: 0cm; padding-bottom: 0cm; border-left: 0.018cm solid #000000; border-bottom: 0.018cm solid #000000 114 Næstved Havn padding-left: 0.15cm; padding-right: 0.15cm; padding-top: 0cm; padding-bottom: 0cm; border-left: 0.018cm solid #000000; border-bottom: 0.018cm solid #000000 161 Kr. 36.925,04 padding-left: 0.15cm; padding-right: 0.15cm; padding-top: 0cm; padding-bottom: 0cm; border-left: 0.018cm solid #000000; border-right: 0.018cm solid #000000; border-bottom: 0.018cm solid #000000 133 Fredericia Havn padding-left: 0.15cm; padding-right: 0.15cm; padding-top: 0cm; padding-bottom: 0cm; border-left: 0.018cm solid #000000; border-bottom: 0.018cm solid #000000 187 Kr. 2.060.649,33 padding-left: 0.15cm; padding-right: 0.15cm; padding-top: 0cm; padding-bottom: 0cm; border-left: 0.018cm solid #000000; border-bottom: 0.018cm solid #000000 114 Odense padding-left: 0.15cm; padding-right: 0.15cm; padding-top: 0cm; padding-bottom: 0cm; border-left: 0.018cm solid #000000; border-bottom: 0.018cm solid #000000 161 Kr. 178.371,91 padding-left: 0.15cm; padding-right: 0.15cm; padding-top: 0cm; padding-bottom: 0cm; border-left: 0.018cm solid #000000; border-right: 0.018cm solid #000000; border-bottom: 0.018cm solid #000000 133 Frederikshavn Havn padding-left: 0.15cm; padding-right: 0.15cm; padding-top: 0cm; padding-bottom: 0cm; border-left: 0.018cm solid #000000; border-bottom: 0.018cm solid #000000 187 Kr. 288.352,73 padding-left: 0.15cm; padding-right: 0.15cm; padding-top: 0cm; padding-bottom: 0cm; border-left: 0.018cm solid #000000; border-bottom: 0.018cm solid #000000 114 Orehoved Havn padding-left: 0.15cm; padding-right: 0.15cm; padding-top: 0cm; padding-bottom: 0cm; border-left: 0.018cm solid #000000; border-bottom: 0.018cm solid #000000 161 Kr. 2.420,36 padding-left: 0.15cm; padding-right: 0.15cm; padding-top: 0cm; padding-bottom: 0cm; border-left: 0.018cm solid #000000; border-right: 0.018cm solid #000000; border-bottom: 0.018cm solid #000000 133 Gedser Havn padding-left: 0.15cm; padding-right: 0.15cm; padding-top: 0cm; padding-bottom: 0cm; border-left: 0.018cm solid #000000; border-bottom: 0.018cm solid #000000 187 Kr. 112.387,31 padding-left: 0.15cm; padding-right: 0.15cm; padding-top: 0cm; padding-bottom: 0cm; border-left: 0.018cm solid #000000; border-bottom: 0.018cm solid #000000 114 Randers Havn padding-left: 0.15cm; padding-right: 0.15cm; padding-top: 0cm; padding-bottom: 0cm; border-left: 0.018cm solid #000000; border-bottom: 0.018cm solid #000000 161 Kr. 81.527,03 padding-left: 0.15cm; padding-right: 0.15cm; padding-top: 0cm; padding-bottom: 0cm; border-left: 0.018cm solid #000000; border-right: 0.018cm solid #000000; border-bottom: 0.018cm solid #000000 133 Grenaa Havn padding-left: 0.15cm; padding-right: 0.15cm; padding-top: 0cm; padding-bottom: 0cm; border-left: 0.018cm solid #000000; border-bottom: 0.018cm solid #000000 187 Kr. 108.192,57 padding-left: 0.15cm; padding-right: 0.15cm; padding-top: 0cm; padding-bottom: 0cm; border-left: 0.018cm solid #000000; border-bottom: 0.018cm solid #000000 114 Rudkøbing Havn padding-left: 0.15cm; padding-right: 0.15cm; padding-top: 0cm; padding-bottom: 0cm; border-left: 0.018cm solid #000000; border-bottom: 0.018cm solid #000000 161 Kr. 6.565,19 padding-left: 0.15cm; padding-right: 0.15cm; padding-top: 0cm; padding-bottom: 0cm; border-left: 0.018cm solid #000000; border-right: 0.018cm solid #000000; border-bottom: 0.018cm solid #000000 133 Gulf-havnen padding-left: 0.15cm; padding-right: 0.15cm; padding-top: 0cm; padding-bottom: 0cm; border-left: 0.018cm solid #000000; border-bottom: 0.018cm solid #000000 187 Kr. 32.537,62 padding-left: 0.15cm; padding-right: 0.15cm; padding-top: 0cm; padding-bottom: 0cm; border-left: 0.018cm solid #000000; border-bottom: 0.018cm solid #000000 114 Rødby Færgehavn padding-left: 0.15cm; padding-right: 0.15cm; padding-top: 0cm; padding-bottom: 0cm; border-left: 0.018cm solid #000000; border-bottom: 0.018cm solid #000000 161 Kr. 403.709,34 padding-left: 0.15cm; padding-right: 0.15cm; padding-top: 0cm; padding-bottom: 0cm; border-left: 0.018cm solid #000000; border-right: 0.018cm solid #000000; border-bottom: 0.018cm solid #000000 133 Haderslev Havn padding-left: 0.15cm; padding-right: 0.15cm; padding-top: 0cm; padding-bottom: 0cm; border-left: 0.018cm solid #000000; border-bottom: 0.018cm solid #000000 187 Kr. 7.646,45 padding-left: 0.15cm; padding-right: 0.15cm; padding-top: 0cm; padding-bottom: 0cm; border-left: 0.018cm solid #000000; border-bottom: 0.018cm solid #000000 114 Rønne Havn padding-left: 0.15cm; padding-right: 0.15cm; padding-top: 0cm; padding-bottom: 0cm; border-left: 0.018cm solid #000000; border-bottom: 0.018cm solid #000000 161 Kr. 139.108,30 padding-left: 0.15cm; padding-right: 0.15cm; padding-top: 0cm; padding-bottom: 0cm; border-left: 0.018cm solid #000000; border-right: 0.018cm solid #000000; border-bottom: 0.018cm solid #000000 133 Helsingør Havn padding-left: 0.15cm; padding-right: 0.15cm; padding-top: 0cm; padding-bottom: 0cm; border-left: 0.018cm solid #000000; border-bottom: 0.018cm solid #000000 187 Kr. 160.517,26 padding-left: 0.15cm; padding-right: 0.15cm; padding-top: 0cm; padding-bottom: 0cm; border-left: 0.018cm solid #000000; border-bottom: 0.018cm solid #000000 114 Sjællands Odde Havn padding-left: 0.15cm; padding-right: 0.15cm; padding-top: 0cm; padding-bottom: 0cm; border-left: 0.018cm solid #000000; border-bottom: 0.018cm solid #000000 161 Kr. 519,84 padding-left: 0.15cm; padding-right: 0.15cm; padding-top: 0cm; padding-bottom: 0cm; border-left: 0.018cm solid #000000; border-right: 0.018cm solid #000000; border-bottom: 0.018cm solid #000000 133 Helsingør SCANDLINES padding-left: 0.15cm; padding-right: 0.15cm; padding-top: 0cm; padding-bottom: 0cm; border-left: 0.018cm solid #000000; border-bottom: 0.018cm solid #000000 187 Kr. 257.290,06 padding-left: 0.15cm; padding-right: 0.15cm; padding-top: 0cm; padding-bottom: 0cm; border-left: 0.018cm solid #000000; border-bottom: 0.018cm solid #000000 114 Skagen Havn padding-left: 0.15cm; padding-right: 0.15cm; padding-top: 0cm; padding-bottom: 0cm; border-left: 0.018cm solid #000000; border-bottom: 0.018cm solid #000000 161 Kr. 28.146,04 padding-left: 0.15cm; padding-right: 0.15cm; padding-top: 0cm; padding-bottom: 0cm; border-left: 0.018cm solid #000000; border-right: 0.018cm solid #000000; border-bottom: 0.018cm solid #000000 133 Hobro-Mariager Havne padding-left: 0.15cm; padding-right: 0.15cm; padding-top: 0cm; padding-bottom: 0cm; border-left: 0.018cm solid #000000; border-bottom: 0.018cm solid #000000 187 Kr. 40.250,61 padding-left: 0.15cm; padding-right: 0.15cm; padding-top: 0cm; padding-bottom: 0cm; border-left: 0.018cm solid #000000; border-bottom: 0.018cm solid #000000 114 Statoil-havnen padding-left: 0.15cm; padding-right: 0.15cm; padding-top: 0cm; padding-bottom: 0cm; border-left: 0.018cm solid #000000; border-bottom: 0.018cm solid #000000 161 Kr. 1.023.512,72 padding-left: 0.15cm; padding-right: 0.15cm; padding-top: 0cm; padding-bottom: 0cm; border-left: 0.018cm solid #000000; border-right: 0.018cm solid #000000; border-bottom: 0.018cm solid #000000 133 Horsens Havn padding-left: 0.15cm; padding-right: 0.15cm; padding-top: 0cm; padding-bottom: 0cm; border-left: 0.018cm solid #000000; border-bottom: 0.018cm solid #000000 187 Kr. 52.693,42 padding-left: 0.15cm; padding-right: 0.15cm; padding-top: 0cm; padding-bottom: 0cm; border-left: 0.018cm solid #000000; border-bottom: 0.018cm solid #000000 114 Stigsnæsværkets Havn padding-left: 0.15cm; padding-right: 0.15cm; padding-top: 0cm; padding-bottom: 0cm; border-left: 0.018cm solid #000000; border-bottom: 0.018cm solid #000000 161 Kr. 102.692,01 padding-left: 0.15cm; padding-right: 0.15cm; padding-top: 0cm; padding-bottom: 0cm; border-left: 0.018cm solid #000000; border-right: 0.018cm solid #000000; border-bottom: 0.018cm solid #000000 133 Hundested Havn padding-left: 0.15cm; padding-right: 0.15cm; padding-top: 0cm; padding-bottom: 0cm; border-left: 0.018cm solid #000000; border-bottom: 0.018cm solid #000000 187 Kr. 29.683,37 padding-left: 0.15cm; padding-right: 0.15cm; padding-top: 0cm; padding-bottom: 0cm; border-left: 0.018cm solid #000000; border-bottom: 0.018cm solid #000000 114 Stubbekøbing Havn padding-left: 0.15cm; padding-right: 0.15cm; padding-top: 0cm; padding-bottom: 0cm; border-left: 0.018cm solid #000000; border-bottom: 0.018cm solid #000000 161 Kr. 13.000,08 padding-left: 0.15cm; padding-right: 0.15cm; padding-top: 0cm; padding-bottom: 0cm; border-left: 0.018cm solid #000000; border-right: 0.018cm solid #000000; border-bottom: 0.018cm solid #000000 133 Kalundborg Havn padding-left: 0.15cm; padding-right: 0.15cm; padding-top: 0cm; padding-bottom: 0cm; border-left: 0.018cm solid #000000; border-bottom: 0.018cm solid #000000 187 Kr. 405.098,35 padding-left: 0.15cm; padding-right: 0.15cm; padding-top: 0cm; padding-bottom: 0cm; border-left: 0.018cm solid #000000; border-bottom: 0.018cm solid #000000 114 Studstrupværkets Havn padding-left: 0.15cm; padding-right: 0.15cm; padding-top: 0cm; padding-bottom: 0cm; border-left: 0.018cm solid #000000; border-bottom: 0.018cm solid #000000 161 Kr. 136.837,66 padding-left: 0.15cm; padding-right: 0.15cm; padding-top: 0cm; padding-bottom: 0cm; border-left: 0.018cm solid #000000; border-right: 0.018cm solid #000000; border-bottom: 0.018cm solid #000000 133 Kolby Kås Havn padding-left: 0.15cm; padding-right: 0.15cm; padding-top: 0cm; padding-bottom: 0cm; border-left: 0.018cm solid #000000; border-bottom: 0.018cm solid #000000 187 Kr. 6.254,68 padding-left: 0.15cm; padding-right: 0.15cm; padding-top: 0cm; padding-bottom: 0cm; border-left: 0.018cm solid #000000; border-bottom: 0.018cm solid #000000 114 Stålvalseværkets Havn padding-left: 0.15cm; padding-right: 0.15cm; padding-top: 0cm; padding-bottom: 0cm; border-left: 0.018cm solid #000000; border-bottom: 0.018cm solid #000000 161 Kr. 108.724,89 padding-left: 0.15cm; padding-right: 0.15cm; padding-top: 0cm; padding-bottom: 0cm; border-left: 0.018cm solid #000000; border-right: 0.018cm solid #000000; border-bottom: 0.018cm solid #000000 133 Kolding Havn padding-left: 0.15cm; padding-right: 0.15cm; padding-top: 0cm; padding-bottom: 0cm; border-left: 0.018cm solid #000000; border-bottom: 0.018cm solid #000000 187 Kr. 114.260,11 padding-left: 0.15cm; padding-right: 0.15cm; padding-top: 0cm; padding-bottom: 0cm; border-left: 0.018cm solid #000000; border-bottom: 0.018cm solid #000000 114 Svendborg Havn padding-left: 0.15cm; padding-right: 0.15cm; padding-top: 0cm; padding-bottom: 0cm; border-left: 0.018cm solid #000000; border-bottom: 0.018cm solid #000000 161 Kr. 21.458,86 padding-left: 0.15cm; padding-right: 0.15cm; padding-top: 0cm; padding-bottom: 0cm; border-left: 0.018cm solid #000000; border-right: 0.018cm solid #000000; border-bottom: 0.018cm solid #000000 133 Korsør Havn padding-left: 0.15cm; padding-right: 0.15cm; padding-top: 0cm; padding-bottom: 0cm; border-left: 0.018cm solid #000000; border-bottom: 0.018cm solid #000000 187 Kr. 41.944,58 padding-left: 0.15cm; padding-right: 0.15cm; padding-top: 0cm; padding-bottom: 0cm; border-left: 0.018cm solid #000000; border-bottom: 0.018cm solid #000000 114 Søby Havn padding-left: 0.15cm; padding-right: 0.15cm; padding-top: 0cm; padding-bottom: 0cm; border-left: 0.018cm solid #000000; border-bottom: 0.018cm solid #000000 161 Kr. 10.504,86 padding-left: 0.15cm; padding-right: 0.15cm; padding-top: 0cm; padding-bottom: 0cm; border-left: 0.018cm solid #000000; border-right: 0.018cm solid #000000; border-bottom: 0.018cm solid #000000 133 Kyndbyværkets Havn padding-left: 0.15cm; padding-right: 0.15cm; padding-top: 0cm; padding-bottom: 0cm; border-left: 0.018cm solid #000000; border-bottom: 0.018cm solid #000000 187 Kr. 4.503,87 padding-left: 0.15cm; padding-right: 0.15cm; padding-top: 0cm; padding-bottom: 0cm; border-left: 0.018cm solid #000000; border-bottom: 0.018cm solid #000000 114 Sønderborg Havn padding-left: 0.15cm; padding-right: 0.15cm; padding-top: 0cm; padding-bottom: 0cm; border-left: 0.018cm solid #000000; border-bottom: 0.018cm solid #000000 161 Kr. 3.243,78 padding-left: 0.15cm; padding-right: 0.15cm; padding-top: 0cm; padding-bottom: 0cm; border-left: 0.018cm solid #000000; border-right: 0.018cm solid #000000; border-bottom: 0.018cm solid #000000 133 Københavns Havn padding-left: 0.15cm; padding-right: 0.15cm; padding-top: 0cm; padding-bottom: 0cm; border-left: 0.018cm solid #000000; border-bottom: 0.018cm solid #000000 187 Kr. 672.523,14 padding-left: 0.15cm; padding-right: 0.15cm; padding-top: 0cm; padding-bottom: 0cm; border-left: 0.018cm solid #000000; border-bottom: 0.018cm solid #000000 114 Vejle Havn padding-left: 0.15cm; padding-right: 0.15cm; padding-top: 0cm; padding-bottom: 0cm; border-left: 0.018cm solid #000000; border-bottom: 0.018cm solid #000000 161 Kr. 82.849,49 padding-left: 0.15cm; padding-right: 0.15cm; padding-top: 0cm; padding-bottom: 0cm; border-left: 0.018cm solid #000000; border-right: 0.018cm solid #000000; border-bottom: 0.018cm solid #000000 133 Køge Havn padding-left: 0.15cm; padding-right: 0.15cm; padding-top: 0cm; padding-bottom: 0cm; border-left: 0.018cm solid #000000; border-bottom: 0.018cm solid #000000 187 Kr. 153.868,89 padding-left: 0.15cm; padding-right: 0.15cm; padding-top: 0cm; padding-bottom: 0cm; border-left: 0.018cm solid #000000; border-bottom: 0.018cm solid #000000 114 Vordingborg Havn padding-left: 0.15cm; padding-right: 0.15cm; padding-top: 0cm; padding-bottom: 0cm; border-left: 0.018cm solid #000000; border-bottom: 0.018cm solid #000000 161 Kr. 18.075,07 padding-left: 0.15cm; padding-right: 0.15cm; padding-top: 0cm; padding-bottom: 0cm; border-left: 0.018cm solid #000000; border-right: 0.018cm solid #000000; border-bottom: 0.018cm solid #000000 133 Lindø Skibsværfts Havn padding-left: 0.15cm; padding-right: 0.15cm; padding-top: 0cm; padding-bottom: 0cm; border-left: 0.018cm solid #000000; border-bottom: 0.018cm solid #000000 187 Kr. 22.316,94 padding-left: 0.15cm; padding-right: 0.15cm; padding-top: 0cm; padding-bottom: 0cm; border-left: 0.018cm solid #000000; border-bottom: 0.018cm solid #000000 114 Aabenraa Havn padding-left: 0.15cm; padding-right: 0.15cm; padding-top: 0cm; padding-bottom: 0cm; border-left: 0.018cm solid #000000; border-bottom: 0.018cm solid #000000 161 Kr. 165.906,92 padding-left: 0.15cm; padding-right: 0.15cm; padding-top: 0cm; padding-bottom: 0cm; border-left: 0.018cm solid #000000; border-right: 0.018cm solid #000000; border-bottom: 0.018cm solid #000000 133 Lyngs Odde Havn padding-left: 0.15cm; padding-right: 0.15cm; padding-top: 0cm; padding-bottom: 0cm; border-left: 0.018cm solid #000000; border-bottom: 0.018cm solid #000000 187 Kr. 20.333,24 padding-left: 0.15cm; padding-right: 0.15cm; padding-top: 0cm; padding-bottom: 0cm; border-left: 0.018cm solid #000000; border-bottom: 0.018cm solid #000000 114 Aalborg Havn padding-left: 0.15cm; padding-right: 0.15cm; padding-top: 0cm; padding-bottom: 0cm; border-left: 0.018cm solid #000000; border-bottom: 0.018cm solid #000000 161 Kr. 617.327,57 padding-left: 0.15cm; padding-right: 0.15cm; padding-top: 0cm; padding-bottom: 0cm; border-left: 0.018cm solid #000000; border-right: 0.018cm solid #000000; border-bottom: 0.018cm solid #000000 133 Middelfart Havn padding-left: 0.15cm; padding-right: 0.15cm; padding-top: 0cm; padding-bottom: 0cm; border-left: 0.018cm solid #000000; border-bottom: 0.018cm solid #000000 187 Kr. 7.211,17 padding-left: 0.15cm; padding-right: 0.15cm; padding-top: 0cm; padding-bottom: 0cm; border-left: 0.018cm solid #000000; border-bottom: 0.018cm solid #000000 114 Århus Havn padding-left: 0.15cm; padding-right: 0.15cm; padding-top: 0cm; padding-bottom: 0cm; border-left: 0.018cm solid #000000; border-bottom: 0.018cm solid #000000 161 Kr. 1.133.560,07 padding-left: 0.15cm; padding-right: 0.15cm; padding-top: 0cm; padding-bottom: 0cm; border-left: 0.018cm solid #000000; border-right: 0.018cm solid #000000; border-bottom: 0.018cm solid #000000 133 Nakskov Havn padding-left: 0.15cm; padding-right: 0.15cm; padding-top: 0cm; padding-bottom: 0cm; border-left: 0.018cm solid #000000; border-bottom: 0.018cm solid #000000 187 Kr. 55.892,84 padding-left: 0.15cm; padding-right: 0.15cm; padding-top: 0cm; padding-bottom: 0cm; border-left: 0.018cm solid #000000; border-bottom: 0.018cm solid #000000 114 padding-left: 0.15cm; padding-right: 0.15cm; padding-top: 0cm; padding-bottom: 0cm; border-left: 0.018cm solid #000000; border-bottom: 0.018cm solid #000000 161 padding-left: 0.15cm; padding-right: 0.15cm; padding-top: 0cm; padding-bottom: 0cm; border-left: 0.018cm solid #000000; border-right: 0.018cm solid #000000; border-bottom: 0.018cm solid #000000 133 SchultzColumns: 187 114 161 133; 0 0 0 left 595"
    },
    {
      "provision_ref": "3",
      "section": "3",
      "content": "§ 3. Isafgiften tilfalder statskassen. Den kan efter vedkommende havnebestyrelses valg enten opkræves af havnebestyrelsen som en afgift af de i havnen ud- og indskibede varemængder eller udredes af havnens almindelige indtægter. Afgiften kan ikke opkræves som en afgift af skibene."
    },
    {
      "provision_ref": "4",
      "section": "4",
      "content": "§ 4. De i § 2 nævnte havne betaler ikke særskilt vederlag for hjælp af Statens Istjenestes isbrydere eller for andre af Statens Istjeneste til isbrydning benyttede skibe. Hvor særlige forhold måtte begrunde dette, kan istjenesten dog betinge sig hel eller delvis dækning af afholdte udgifter."
    },
    {
      "provision_ref": "5",
      "section": "5",
      "content": "§ 5. Bekendtgørelsen træder i kraft den 1. januar 2008. Stk. 2. Bekendtgørelse nr. 1287 af 8. december 2006 om isafgift af de varemængder, der ud- og indskibes i visse danske havne, ophæves."
    }
  ],
  "provision_versions": [
    {
      "provision_ref": "1",
      "section": "1",
      "content": "§ 1. Havne med en vanddybde på 5 m eller derover beliggende inden for Skagen skal betale en årlig afgift som bidrag til dækning af udgifterne ved driften af Statens Istjeneste .",
      "valid_from": "2007-10-04",
      "valid_to": null
    },
    {
      "provision_ref": "2",
      "section": "2",
      "content": "§ 2. Isafgiften vil fra og med 1. januar 2008 være at udrede med følgende beløb : Asnæsværkets Havn padding-left: 0.15cm; padding-right: 0.15cm; padding-top: 0cm; padding-bottom: 0cm; border-left: 0.018cm solid #000000; border-top: 0.018cm solid #000000; border-bottom: 0.018cm solid #000000 187 Kr. 192.863,58 padding-left: 0.15cm; padding-right: 0.15cm; padding-top: 0cm; padding-bottom: 0cm; border-left: 0.018cm solid #000000; border-top: 0.018cm solid #000000; border-bottom: 0.018cm solid #000000 114 Nexø Havn padding-left: 0.15cm; padding-right: 0.15cm; padding-top: 0cm; padding-bottom: 0cm; border-left: 0.018cm solid #000000; border-top: 0.018cm solid #000000; border-bottom: 0.018cm solid #000000 161 Kr. 3.859,27 padding-left: 0.15cm; padding-right: 0.15cm; padding-top: 0cm; padding-bottom: 0cm; border: 0.018cm solid #000000 133 Assens Havn padding-left: 0.15cm; padding-right: 0.15cm; padding-top: 0cm; padding-bottom: 0cm; border-left: 0.018cm solid #000000; border-bottom: 0.018cm solid #000000 187 Kr. 16.967,47 padding-left: 0.15cm; padding-right: 0.15cm; padding-top: 0cm; padding-bottom: 0cm; border-left: 0.018cm solid #000000; border-bottom: 0.018cm solid #000000 114 Nordjyllandsværkets Havn padding-left: 0.15cm; padding-right: 0.15cm; padding-top: 0cm; padding-bottom: 0cm; border-left: 0.018cm solid #000000; border-bottom: 0.018cm solid #000000 161 Kr. 113.413,12 padding-left: 0.15cm; padding-right: 0.15cm; padding-top: 0cm; padding-bottom: 0cm; border-left: 0.018cm solid #000000; border-right: 0.018cm solid #000000; border-bottom: 0.018cm solid #000000 133 Avedøreværkets Havn padding-left: 0.15cm; padding-right: 0.15cm; padding-top: 0cm; padding-bottom: 0cm; border-left: 0.018cm solid #000000; border-bottom: 0.018cm solid #000000 187 Kr. 109.964,18 padding-left: 0.15cm; padding-right: 0.15cm; padding-top: 0cm; padding-bottom: 0cm; border-left: 0.018cm solid #000000; border-bottom: 0.018cm solid #000000 114 Nyborg Havn padding-left: 0.15cm; padding-right: 0.15cm; padding-top: 0cm; padding-bottom: 0cm; border-left: 0.018cm solid #000000; border-bottom: 0.018cm solid #000000 161 Kr. 59.763,20 padding-left: 0.15cm; padding-right: 0.15cm; padding-top: 0cm; padding-bottom: 0cm; border-left: 0.018cm solid #000000; border-right: 0.018cm solid #000000; border-bottom: 0.018cm solid #000000 133 Bandholm-Maribo Havn padding-left: 0.15cm; padding-right: 0.15cm; padding-top: 0cm; padding-bottom: 0cm; border-left: 0.018cm solid #000000; border-bottom: 0.018cm solid #000000 187 Kr. 19.163,26 padding-left: 0.15cm; padding-right: 0.15cm; padding-top: 0cm; padding-bottom: 0cm; border-left: 0.018cm solid #000000; border-bottom: 0.018cm solid #000000 114 Nykøbing F. Havn padding-left: 0.15cm; padding-right: 0.15cm; padding-top: 0cm; padding-bottom: 0cm; border-left: 0.018cm solid #000000; border-bottom: 0.018cm solid #000000 161 Kr. 31.168,02 padding-left: 0.15cm; padding-right: 0.15cm; padding-top: 0cm; padding-bottom: 0cm; border-left: 0.018cm solid #000000; border-right: 0.018cm solid #000000; border-bottom: 0.018cm solid #000000 133 Enstedværkets Havn padding-left: 0.15cm; padding-right: 0.15cm; padding-top: 0cm; padding-bottom: 0cm; border-left: 0.018cm solid #000000; border-bottom: 0.018cm solid #000000 187 Kr. 555.684,64 padding-left: 0.15cm; padding-right: 0.15cm; padding-top: 0cm; padding-bottom: 0cm; border-left: 0.018cm solid #000000; border-bottom: 0.018cm solid #000000 114 Næstved Havn padding-left: 0.15cm; padding-right: 0.15cm; padding-top: 0cm; padding-bottom: 0cm; border-left: 0.018cm solid #000000; border-bottom: 0.018cm solid #000000 161 Kr. 36.925,04 padding-left: 0.15cm; padding-right: 0.15cm; padding-top: 0cm; padding-bottom: 0cm; border-left: 0.018cm solid #000000; border-right: 0.018cm solid #000000; border-bottom: 0.018cm solid #000000 133 Fredericia Havn padding-left: 0.15cm; padding-right: 0.15cm; padding-top: 0cm; padding-bottom: 0cm; border-left: 0.018cm solid #000000; border-bottom: 0.018cm solid #000000 187 Kr. 2.060.649,33 padding-left: 0.15cm; padding-right: 0.15cm; padding-top: 0cm; padding-bottom: 0cm; border-left: 0.018cm solid #000000; border-bottom: 0.018cm solid #000000 114 Odense padding-left: 0.15cm; padding-right: 0.15cm; padding-top: 0cm; padding-bottom: 0cm; border-left: 0.018cm solid #000000; border-bottom: 0.018cm solid #000000 161 Kr. 178.371,91 padding-left: 0.15cm; padding-right: 0.15cm; padding-top: 0cm; padding-bottom: 0cm; border-left: 0.018cm solid #000000; border-right: 0.018cm solid #000000; border-bottom: 0.018cm solid #000000 133 Frederikshavn Havn padding-left: 0.15cm; padding-right: 0.15cm; padding-top: 0cm; padding-bottom: 0cm; border-left: 0.018cm solid #000000; border-bottom: 0.018cm solid #000000 187 Kr. 288.352,73 padding-left: 0.15cm; padding-right: 0.15cm; padding-top: 0cm; padding-bottom: 0cm; border-left: 0.018cm solid #000000; border-bottom: 0.018cm solid #000000 114 Orehoved Havn padding-left: 0.15cm; padding-right: 0.15cm; padding-top: 0cm; padding-bottom: 0cm; border-left: 0.018cm solid #000000; border-bottom: 0.018cm solid #000000 161 Kr. 2.420,36 padding-left: 0.15cm; padding-right: 0.15cm; padding-top: 0cm; padding-bottom: 0cm; border-left: 0.018cm solid #000000; border-right: 0.018cm solid #000000; border-bottom: 0.018cm solid #000000 133 Gedser Havn padding-left: 0.15cm; padding-right: 0.15cm; padding-top: 0cm; padding-bottom: 0cm; border-left: 0.018cm solid #000000; border-bottom: 0.018cm solid #000000 187 Kr. 112.387,31 padding-left: 0.15cm; padding-right: 0.15cm; padding-top: 0cm; padding-bottom: 0cm; border-left: 0.018cm solid #000000; border-bottom: 0.018cm solid #000000 114 Randers Havn padding-left: 0.15cm; padding-right: 0.15cm; padding-top: 0cm; padding-bottom: 0cm; border-left: 0.018cm solid #000000; border-bottom: 0.018cm solid #000000 161 Kr. 81.527,03 padding-left: 0.15cm; padding-right: 0.15cm; padding-top: 0cm; padding-bottom: 0cm; border-left: 0.018cm solid #000000; border-right: 0.018cm solid #000000; border-bottom: 0.018cm solid #000000 133 Grenaa Havn padding-left: 0.15cm; padding-right: 0.15cm; padding-top: 0cm; padding-bottom: 0cm; border-left: 0.018cm solid #000000; border-bottom: 0.018cm solid #000000 187 Kr. 108.192,57 padding-left: 0.15cm; padding-right: 0.15cm; padding-top: 0cm; padding-bottom: 0cm; border-left: 0.018cm solid #000000; border-bottom: 0.018cm solid #000000 114 Rudkøbing Havn padding-left: 0.15cm; padding-right: 0.15cm; padding-top: 0cm; padding-bottom: 0cm; border-left: 0.018cm solid #000000; border-bottom: 0.018cm solid #000000 161 Kr. 6.565,19 padding-left: 0.15cm; padding-right: 0.15cm; padding-top: 0cm; padding-bottom: 0cm; border-left: 0.018cm solid #000000; border-right: 0.018cm solid #000000; border-bottom: 0.018cm solid #000000 133 Gulf-havnen padding-left: 0.15cm; padding-right: 0.15cm; padding-top: 0cm; padding-bottom: 0cm; border-left: 0.018cm solid #000000; border-bottom: 0.018cm solid #000000 187 Kr. 32.537,62 padding-left: 0.15cm; padding-right: 0.15cm; padding-top: 0cm; padding-bottom: 0cm; border-left: 0.018cm solid #000000; border-bottom: 0.018cm solid #000000 114 Rødby Færgehavn padding-left: 0.15cm; padding-right: 0.15cm; padding-top: 0cm; padding-bottom: 0cm; border-left: 0.018cm solid #000000; border-bottom: 0.018cm solid #000000 161 Kr. 403.709,34 padding-left: 0.15cm; padding-right: 0.15cm; padding-top: 0cm; padding-bottom: 0cm; border-left: 0.018cm solid #000000; border-right: 0.018cm solid #000000; border-bottom: 0.018cm solid #000000 133 Haderslev Havn padding-left: 0.15cm; padding-right: 0.15cm; padding-top: 0cm; padding-bottom: 0cm; border-left: 0.018cm solid #000000; border-bottom: 0.018cm solid #000000 187 Kr. 7.646,45 padding-left: 0.15cm; padding-right: 0.15cm; padding-top: 0cm; padding-bottom: 0cm; border-left: 0.018cm solid #000000; border-bottom: 0.018cm solid #000000 114 Rønne Havn padding-left: 0.15cm; padding-right: 0.15cm; padding-top: 0cm; padding-bottom: 0cm; border-left: 0.018cm solid #000000; border-bottom: 0.018cm solid #000000 161 Kr. 139.108,30 padding-left: 0.15cm; padding-right: 0.15cm; padding-top: 0cm; padding-bottom: 0cm; border-left: 0.018cm solid #000000; border-right: 0.018cm solid #000000; border-bottom: 0.018cm solid #000000 133 Helsingør Havn padding-left: 0.15cm; padding-right: 0.15cm; padding-top: 0cm; padding-bottom: 0cm; border-left: 0.018cm solid #000000; border-bottom: 0.018cm solid #000000 187 Kr. 160.517,26 padding-left: 0.15cm; padding-right: 0.15cm; padding-top: 0cm; padding-bottom: 0cm; border-left: 0.018cm solid #000000; border-bottom: 0.018cm solid #000000 114 Sjællands Odde Havn padding-left: 0.15cm; padding-right: 0.15cm; padding-top: 0cm; padding-bottom: 0cm; border-left: 0.018cm solid #000000; border-bottom: 0.018cm solid #000000 161 Kr. 519,84 padding-left: 0.15cm; padding-right: 0.15cm; padding-top: 0cm; padding-bottom: 0cm; border-left: 0.018cm solid #000000; border-right: 0.018cm solid #000000; border-bottom: 0.018cm solid #000000 133 Helsingør SCANDLINES padding-left: 0.15cm; padding-right: 0.15cm; padding-top: 0cm; padding-bottom: 0cm; border-left: 0.018cm solid #000000; border-bottom: 0.018cm solid #000000 187 Kr. 257.290,06 padding-left: 0.15cm; padding-right: 0.15cm; padding-top: 0cm; padding-bottom: 0cm; border-left: 0.018cm solid #000000; border-bottom: 0.018cm solid #000000 114 Skagen Havn padding-left: 0.15cm; padding-right: 0.15cm; padding-top: 0cm; padding-bottom: 0cm; border-left: 0.018cm solid #000000; border-bottom: 0.018cm solid #000000 161 Kr. 28.146,04 padding-left: 0.15cm; padding-right: 0.15cm; padding-top: 0cm; padding-bottom: 0cm; border-left: 0.018cm solid #000000; border-right: 0.018cm solid #000000; border-bottom: 0.018cm solid #000000 133 Hobro-Mariager Havne padding-left: 0.15cm; padding-right: 0.15cm; padding-top: 0cm; padding-bottom: 0cm; border-left: 0.018cm solid #000000; border-bottom: 0.018cm solid #000000 187 Kr. 40.250,61 padding-left: 0.15cm; padding-right: 0.15cm; padding-top: 0cm; padding-bottom: 0cm; border-left: 0.018cm solid #000000; border-bottom: 0.018cm solid #000000 114 Statoil-havnen padding-left: 0.15cm; padding-right: 0.15cm; padding-top: 0cm; padding-bottom: 0cm; border-left: 0.018cm solid #000000; border-bottom: 0.018cm solid #000000 161 Kr. 1.023.512,72 padding-left: 0.15cm; padding-right: 0.15cm; padding-top: 0cm; padding-bottom: 0cm; border-left: 0.018cm solid #000000; border-right: 0.018cm solid #000000; border-bottom: 0.018cm solid #000000 133 Horsens Havn padding-left: 0.15cm; padding-right: 0.15cm; padding-top: 0cm; padding-bottom: 0cm; border-left: 0.018cm solid #000000; border-bottom: 0.018cm solid #000000 187 Kr. 52.693,42 padding-left: 0.15cm; padding-right: 0.15cm; padding-top: 0cm; padding-bottom: 0cm; border-left: 0.018cm solid #000000; border-bottom: 0.018cm solid #000000 114 Stigsnæsværkets Havn padding-left: 0.15cm; padding-right: 0.15cm; padding-top: 0cm; padding-bottom: 0cm; border-left: 0.018cm solid #000000; border-bottom: 0.018cm solid #000000 161 Kr. 102.692,01 padding-left: 0.15cm; padding-right: 0.15cm; padding-top: 0cm; padding-bottom: 0cm; border-left: 0.018cm solid #000000; border-right: 0.018cm solid #000000; border-bottom: 0.018cm solid #000000 133 Hundested Havn padding-left: 0.15cm; padding-right: 0.15cm; padding-top: 0cm; padding-bottom: 0cm; border-left: 0.018cm solid #000000; border-bottom: 0.018cm solid #000000 187 Kr. 29.683,37 padding-left: 0.15cm; padding-right: 0.15cm; padding-top: 0cm; padding-bottom: 0cm; border-left: 0.018cm solid #000000; border-bottom: 0.018cm solid #000000 114 Stubbekøbing Havn padding-left: 0.15cm; padding-right: 0.15cm; padding-top: 0cm; padding-bottom: 0cm; border-left: 0.018cm solid #000000; border-bottom: 0.018cm solid #000000 161 Kr. 13.000,08 padding-left: 0.15cm; padding-right: 0.15cm; padding-top: 0cm; padding-bottom: 0cm; border-left: 0.018cm solid #000000; border-right: 0.018cm solid #000000; border-bottom: 0.018cm solid #000000 133 Kalundborg Havn padding-left: 0.15cm; padding-right: 0.15cm; padding-top: 0cm; padding-bottom: 0cm; border-left: 0.018cm solid #000000; border-bottom: 0.018cm solid #000000 187 Kr. 405.098,35 padding-left: 0.15cm; padding-right: 0.15cm; padding-top: 0cm; padding-bottom: 0cm; border-left: 0.018cm solid #000000; border-bottom: 0.018cm solid #000000 114 Studstrupværkets Havn padding-left: 0.15cm; padding-right: 0.15cm; padding-top: 0cm; padding-bottom: 0cm; border-left: 0.018cm solid #000000; border-bottom: 0.018cm solid #000000 161 Kr. 136.837,66 padding-left: 0.15cm; padding-right: 0.15cm; padding-top: 0cm; padding-bottom: 0cm; border-left: 0.018cm solid #000000; border-right: 0.018cm solid #000000; border-bottom: 0.018cm solid #000000 133 Kolby Kås Havn padding-left: 0.15cm; padding-right: 0.15cm; padding-top: 0cm; padding-bottom: 0cm; border-left: 0.018cm solid #000000; border-bottom: 0.018cm solid #000000 187 Kr. 6.254,68 padding-left: 0.15cm; padding-right: 0.15cm; padding-top: 0cm; padding-bottom: 0cm; border-left: 0.018cm solid #000000; border-bottom: 0.018cm solid #000000 114 Stålvalseværkets Havn padding-left: 0.15cm; padding-right: 0.15cm; padding-top: 0cm; padding-bottom: 0cm; border-left: 0.018cm solid #000000; border-bottom: 0.018cm solid #000000 161 Kr. 108.724,89 padding-left: 0.15cm; padding-right: 0.15cm; padding-top: 0cm; padding-bottom: 0cm; border-left: 0.018cm solid #000000; border-right: 0.018cm solid #000000; border-bottom: 0.018cm solid #000000 133 Kolding Havn padding-left: 0.15cm; padding-right: 0.15cm; padding-top: 0cm; padding-bottom: 0cm; border-left: 0.018cm solid #000000; border-bottom: 0.018cm solid #000000 187 Kr. 114.260,11 padding-left: 0.15cm; padding-right: 0.15cm; padding-top: 0cm; padding-bottom: 0cm; border-left: 0.018cm solid #000000; border-bottom: 0.018cm solid #000000 114 Svendborg Havn padding-left: 0.15cm; padding-right: 0.15cm; padding-top: 0cm; padding-bottom: 0cm; border-left: 0.018cm solid #000000; border-bottom: 0.018cm solid #000000 161 Kr. 21.458,86 padding-left: 0.15cm; padding-right: 0.15cm; padding-top: 0cm; padding-bottom: 0cm; border-left: 0.018cm solid #000000; border-right: 0.018cm solid #000000; border-bottom: 0.018cm solid #000000 133 Korsør Havn padding-left: 0.15cm; padding-right: 0.15cm; padding-top: 0cm; padding-bottom: 0cm; border-left: 0.018cm solid #000000; border-bottom: 0.018cm solid #000000 187 Kr. 41.944,58 padding-left: 0.15cm; padding-right: 0.15cm; padding-top: 0cm; padding-bottom: 0cm; border-left: 0.018cm solid #000000; border-bottom: 0.018cm solid #000000 114 Søby Havn padding-left: 0.15cm; padding-right: 0.15cm; padding-top: 0cm; padding-bottom: 0cm; border-left: 0.018cm solid #000000; border-bottom: 0.018cm solid #000000 161 Kr. 10.504,86 padding-left: 0.15cm; padding-right: 0.15cm; padding-top: 0cm; padding-bottom: 0cm; border-left: 0.018cm solid #000000; border-right: 0.018cm solid #000000; border-bottom: 0.018cm solid #000000 133 Kyndbyværkets Havn padding-left: 0.15cm; padding-right: 0.15cm; padding-top: 0cm; padding-bottom: 0cm; border-left: 0.018cm solid #000000; border-bottom: 0.018cm solid #000000 187 Kr. 4.503,87 padding-left: 0.15cm; padding-right: 0.15cm; padding-top: 0cm; padding-bottom: 0cm; border-left: 0.018cm solid #000000; border-bottom: 0.018cm solid #000000 114 Sønderborg Havn padding-left: 0.15cm; padding-right: 0.15cm; padding-top: 0cm; padding-bottom: 0cm; border-left: 0.018cm solid #000000; border-bottom: 0.018cm solid #000000 161 Kr. 3.243,78 padding-left: 0.15cm; padding-right: 0.15cm; padding-top: 0cm; padding-bottom: 0cm; border-left: 0.018cm solid #000000; border-right: 0.018cm solid #000000; border-bottom: 0.018cm solid #000000 133 Københavns Havn padding-left: 0.15cm; padding-right: 0.15cm; padding-top: 0cm; padding-bottom: 0cm; border-left: 0.018cm solid #000000; border-bottom: 0.018cm solid #000000 187 Kr. 672.523,14 padding-left: 0.15cm; padding-right: 0.15cm; padding-top: 0cm; padding-bottom: 0cm; border-left: 0.018cm solid #000000; border-bottom: 0.018cm solid #000000 114 Vejle Havn padding-left: 0.15cm; padding-right: 0.15cm; padding-top: 0cm; padding-bottom: 0cm; border-left: 0.018cm solid #000000; border-bottom: 0.018cm solid #000000 161 Kr. 82.849,49 padding-left: 0.15cm; padding-right: 0.15cm; padding-top: 0cm; padding-bottom: 0cm; border-left: 0.018cm solid #000000; border-right: 0.018cm solid #000000; border-bottom: 0.018cm solid #000000 133 Køge Havn padding-left: 0.15cm; padding-right: 0.15cm; padding-top: 0cm; padding-bottom: 0cm; border-left: 0.018cm solid #000000; border-bottom: 0.018cm solid #000000 187 Kr. 153.868,89 padding-left: 0.15cm; padding-right: 0.15cm; padding-top: 0cm; padding-bottom: 0cm; border-left: 0.018cm solid #000000; border-bottom: 0.018cm solid #000000 114 Vordingborg Havn padding-left: 0.15cm; padding-right: 0.15cm; padding-top: 0cm; padding-bottom: 0cm; border-left: 0.018cm solid #000000; border-bottom: 0.018cm solid #000000 161 Kr. 18.075,07 padding-left: 0.15cm; padding-right: 0.15cm; padding-top: 0cm; padding-bottom: 0cm; border-left: 0.018cm solid #000000; border-right: 0.018cm solid #000000; border-bottom: 0.018cm solid #000000 133 Lindø Skibsværfts Havn padding-left: 0.15cm; padding-right: 0.15cm; padding-top: 0cm; padding-bottom: 0cm; border-left: 0.018cm solid #000000; border-bottom: 0.018cm solid #000000 187 Kr. 22.316,94 padding-left: 0.15cm; padding-right: 0.15cm; padding-top: 0cm; padding-bottom: 0cm; border-left: 0.018cm solid #000000; border-bottom: 0.018cm solid #000000 114 Aabenraa Havn padding-left: 0.15cm; padding-right: 0.15cm; padding-top: 0cm; padding-bottom: 0cm; border-left: 0.018cm solid #000000; border-bottom: 0.018cm solid #000000 161 Kr. 165.906,92 padding-left: 0.15cm; padding-right: 0.15cm; padding-top: 0cm; padding-bottom: 0cm; border-left: 0.018cm solid #000000; border-right: 0.018cm solid #000000; border-bottom: 0.018cm solid #000000 133 Lyngs Odde Havn padding-left: 0.15cm; padding-right: 0.15cm; padding-top: 0cm; padding-bottom: 0cm; border-left: 0.018cm solid #000000; border-bottom: 0.018cm solid #000000 187 Kr. 20.333,24 padding-left: 0.15cm; padding-right: 0.15cm; padding-top: 0cm; padding-bottom: 0cm; border-left: 0.018cm solid #000000; border-bottom: 0.018cm solid #000000 114 Aalborg Havn padding-left: 0.15cm; padding-right: 0.15cm; padding-top: 0cm; padding-bottom: 0cm; border-left: 0.018cm solid #000000; border-bottom: 0.018cm solid #000000 161 Kr. 617.327,57 padding-left: 0.15cm; padding-right: 0.15cm; padding-top: 0cm; padding-bottom: 0cm; border-left: 0.018cm solid #000000; border-right: 0.018cm solid #000000; border-bottom: 0.018cm solid #000000 133 Middelfart Havn padding-left: 0.15cm; padding-right: 0.15cm; padding-top: 0cm; padding-bottom: 0cm; border-left: 0.018cm solid #000000; border-bottom: 0.018cm solid #000000 187 Kr. 7.211,17 padding-left: 0.15cm; padding-right: 0.15cm; padding-top: 0cm; padding-bottom: 0cm; border-left: 0.018cm solid #000000; border-bottom: 0.018cm solid #000000 114 Århus Havn padding-left: 0.15cm; padding-right: 0.15cm; padding-top: 0cm; padding-bottom: 0cm; border-left: 0.018cm solid #000000; border-bottom: 0.018cm solid #000000 161 Kr. 1.133.560,07 padding-left: 0.15cm; padding-right: 0.15cm; padding-top: 0cm; padding-bottom: 0cm; border-left: 0.018cm solid #000000; border-right: 0.018cm solid #000000; border-bottom: 0.018cm solid #000000 133 Nakskov Havn padding-left: 0.15cm; padding-right: 0.15cm; padding-top: 0cm; padding-bottom: 0cm; border-left: 0.018cm solid #000000; border-bottom: 0.018cm solid #000000 187 Kr. 55.892,84 padding-left: 0.15cm; padding-right: 0.15cm; padding-top: 0cm; padding-bottom: 0cm; border-left: 0.018cm solid #000000; border-bottom: 0.018cm solid #000000 114 padding-left: 0.15cm; padding-right: 0.15cm; padding-top: 0cm; padding-bottom: 0cm; border-left: 0.018cm solid #000000; border-bottom: 0.018cm solid #000000 161 padding-left: 0.15cm; padding-right: 0.15cm; padding-top: 0cm; padding-bottom: 0cm; border-left: 0.018cm solid #000000; border-right: 0.018cm solid #000000; border-bottom: 0.018cm solid #000000 133 SchultzColumns: 187 114 161 133; 0 0 0 left 595",
      "valid_from": "2007-10-04",
      "valid_to": null
    },
    {
      "provision_ref": "3",
      "section": "3",
      "content": "§ 3. Isafgiften tilfalder statskassen. Den kan efter vedkommende havnebestyrelses valg enten opkræves af havnebestyrelsen som en afgift af de i havnen ud- og indskibede varemængder eller udredes af havnens almindelige indtægter. Afgiften kan ikke opkræves som en afgift af skibene.",
      "valid_from": "2007-10-04",
      "valid_to": null
    },
    {
      "provision_ref": "4",
      "section": "4",
      "content": "§ 4. De i § 2 nævnte havne betaler ikke særskilt vederlag for hjælp af Statens Istjenestes isbrydere eller for andre af Statens Istjeneste til isbrydning benyttede skibe. Hvor særlige forhold måtte begrunde dette, kan istjenesten dog betinge sig hel eller delvis dækning af afholdte udgifter.",
      "valid_from": "2007-10-04",
      "valid_to": null
    },
    {
      "provision_ref": "5",
      "section": "5",
      "content": "§ 5. Bekendtgørelsen træder i kraft den 1. januar 2008. Stk. 2. Bekendtgørelse nr. 1287 af 8. december 2006 om isafgift af de varemængder, der ud- og indskibes i visse danske havne, ophæves.",
      "valid_from": "2007-10-04",
      "valid_to": null
    }
  ],
  "definitions": []
}
