{
  "id": "2009:423",
  "type": "statute",
  "title": "Bekendtgørelse om ændring af bekendtgørelse om udenretlige inddrivelsesomkostninger i anledning af forsinket betaling",
  "short_name": "BEK Æ#LOKDOK05",
  "status": "in_force",
  "issued_date": "2009-05-28",
  "url": "https://www.retsinformation.dk/eli/lta/2009/423/xml",
  "description": "Retsinformation source. DocumentId=AA004847; AccessionNumber=B20090042305; Characters preserved in NFC; ASCII fallback used only for key/file generation.",
  "provisions": [],
  "provision_versions": [],
  "definitions": []
}
