{
  "id": "2011:72",
  "type": "statute",
  "title": "Lov om ændring af lov om anvendelsen af visse af Det Europæiske Fællesskabs retsakter om økonomiske forbindelser til tredjelande m.v.\\n(Gebyr for behandling af ansøgninger m.v.)",
  "short_name": "LOV Æ#LOKDOK02",
  "status": "in_force",
  "issued_date": "2011-02-01",
  "url": "https://www.retsinformation.dk/eli/lta/2011/72/xml",
  "description": "Retsinformation source. DocumentId=AU004323; AccessionNumber=A20110007230; Characters preserved in NFC; ASCII fallback used only for key/file generation.",
  "provisions": [],
  "provision_versions": [],
  "definitions": []
}
