{
  "id": "2012:586",
  "type": "statute",
  "title": "Lov om ændring af regionsloven\\n(Indførelse af dispensationsadgang til regioners nedsættelse af stående udvalg)",
  "short_name": "LOV Æ#LOKDOK02",
  "status": "in_force",
  "issued_date": "2012-06-18",
  "url": "https://www.retsinformation.dk/eli/lta/2012/586/xml",
  "description": "Retsinformation source. DocumentId=BX000088; AccessionNumber=A20120058630; Characters preserved in NFC; ASCII fallback used only for key/file generation.",
  "provisions": [],
  "provision_versions": [],
  "definitions": []
}
