{
  "id": "2013:947",
  "type": "statute",
  "title": "Bekendtgørelse om ændring af bekendtgørelse om bekæmpelsesmidler\\n(Nyt biocidaktivstof samt beslutninger om at udfase pesticid- og biocidaktivstoffer)",
  "short_name": "BEK Æ#LOKDOK05",
  "status": "in_force",
  "issued_date": "2013-07-05",
  "url": "https://www.retsinformation.dk/eli/lta/2013/947/xml",
  "description": "Retsinformation source. DocumentId=AL002857; AccessionNumber=B20130094705; Characters preserved in NFC; ASCII fallback used only for key/file generation.",
  "provisions": [],
  "provision_versions": [],
  "definitions": []
}
