{
  "id": "2015:743",
  "type": "statute",
  "title": "Lov om ændring af lov om vederlag og pension m.v. for ministre (Forlængelse af perioden for midlertidig nedsættelse af grundvederlag til ministre)",
  "short_name": "LOV Æ#LOKDOK02",
  "status": "in_force",
  "issued_date": "2015-06-01",
  "url": "https://www.retsinformation.dk/eli/lta/2015/743/xml",
  "description": "Retsinformation source. DocumentId=AE002188; AccessionNumber=A20150074330; Characters preserved in NFC; ASCII fallback used only for key/file generation.",
  "provisions": [],
  "provision_versions": [],
  "definitions": []
}
