{
  "id": "2016:1153",
  "type": "statute",
  "title": "Bekendtgørelse om ændring af bekendtgørelse om særlig lånemulighed i forbindelse med uddannelsesløft",
  "short_name": "BEK Æ#LOKDOK05",
  "status": "in_force",
  "issued_date": "2016-09-02",
  "url": "https://www.retsinformation.dk/eli/lta/2016/1153/xml",
  "description": "Retsinformation source. DocumentId=BE006945; AccessionNumber=B20160115305; Characters preserved in NFC; ASCII fallback used only for key/file generation.",
  "provisions": [],
  "provision_versions": [],
  "definitions": []
}
