{
  "id": "2021:2536",
  "type": "statute",
  "title": "Bekendtgørelse om håndbog om dokumentation for opfyldelse af CO2e-fortrængningskrav m.v. (HB 2022)",
  "short_name": "BEK H#LOKDOK04",
  "status": "in_force",
  "issued_date": "2021-12-14",
  "url": "https://www.retsinformation.dk/eli/lta/2021/2536/xml",
  "description": "Retsinformation source. DocumentId=DB000428; AccessionNumber=B20210253605; Characters preserved in NFC; ASCII fallback used only for key/file generation.",
  "provisions": [
    {
      "provision_ref": "1:1",
      "chapter": "1",
      "section": "1",
      "content": "§ 1. Hermed offentliggøres håndbog om dokumentation for opfyldelse af CO 2 e-fortrængningskrav m.v. (HB 2022), som angivet i bilag 1 til denne bekendtgørelse."
    },
    {
      "provision_ref": "1:2",
      "chapter": "1",
      "section": "2",
      "content": "§ 2. Bekendtgørelsen træder i kraft den 1. januar 2022. Stk. 2. Bekendtgørelse nr. 91 af 25. januar 2021 om Håndbog om dokumentation for biobrændstoffers bæredygtighed (HB 2021) ophæves."
    }
  ],
  "provision_versions": [
    {
      "provision_ref": "1:1",
      "chapter": "1",
      "section": "1",
      "content": "§ 1. Hermed offentliggøres håndbog om dokumentation for opfyldelse af CO 2 e-fortrængningskrav m.v. (HB 2022), som angivet i bilag 1 til denne bekendtgørelse.",
      "valid_from": "2021-12-14",
      "valid_to": null
    },
    {
      "provision_ref": "1:2",
      "chapter": "1",
      "section": "2",
      "content": "§ 2. Bekendtgørelsen træder i kraft den 1. januar 2022. Stk. 2. Bekendtgørelse nr. 91 af 25. januar 2021 om Håndbog om dokumentation for biobrændstoffers bæredygtighed (HB 2021) ophæves.",
      "valid_from": "2021-12-14",
      "valid_to": null
    }
  ],
  "definitions": []
}
