{
  "id": "2021:464",
  "type": "statute",
  "title": "Bekendtgørelse om ændring af bekendtgørelse om forbud mod adgang til og restriktioner for lokaler og lokaliteter, krav om mundbind m.v. og covid-19-test på Erhvervsministeriets område i forbindelse med håndtering af covid-19",
  "short_name": "BEK Æ#LOKDOK05",
  "status": "in_force",
  "issued_date": "2021-03-18",
  "url": "https://www.retsinformation.dk/eli/lta/2021/464/xml",
  "description": "Retsinformation source. DocumentId=CQ001670; AccessionNumber=B20210046405; Characters preserved in NFC; ASCII fallback used only for key/file generation.",
  "provisions": [],
  "provision_versions": [],
  "definitions": []
}
