{
  "id": "2022:1370",
  "type": "statute",
  "title": "Bekendtgørelse om ændring af bekendtgørelse om regnskabsaflæggelse, rapportering og revision vedrørende Børne- og Undervisningsministeriets puljemidler m.v.",
  "short_name": "BEK Æ#LOKDOK05",
  "status": "in_force",
  "issued_date": "2022-09-28",
  "url": "https://www.retsinformation.dk/eli/lta/2022/1370/xml",
  "description": "Retsinformation source. DocumentId=DA000978; AccessionNumber=B20220137005; Characters preserved in NFC; ASCII fallback used only for key/file generation.",
  "provisions": [],
  "provision_versions": [],
  "definitions": []
}
