{
  "id": "2023:1783",
  "type": "statute",
  "title": "Lov om ændring af databeskyttelsesloven (Justering af aldersgrænsen for samtykke til behandling af personoplysninger i forbindelse med udbud af informationssamfundstjenester)",
  "short_name": "LOV Æ#LOKDOK02",
  "status": "in_force",
  "issued_date": "2023-12-28",
  "url": "https://www.retsinformation.dk/eli/lta/2023/1783/xml",
  "description": "Retsinformation source. DocumentId=AA014011; AccessionNumber=A20230178330; Characters preserved in NFC; ASCII fallback used only for key/file generation.",
  "provisions": [],
  "provision_versions": [],
  "definitions": []
}
