{
  "id": "2024:1263",
  "type": "statute",
  "title": "Bekendtgørelse om ændring af bekendtgørelse om folkeskolens specialpædagogiske bistand til børn, der endnu ikke har påbegyndt skolegangen",
  "short_name": "BEK Æ#LOKDOK05",
  "status": "in_force",
  "issued_date": "2024-11-28",
  "url": "https://www.retsinformation.dk/eli/lta/2024/1263/xml",
  "description": "Retsinformation source. DocumentId=DA001465; AccessionNumber=B20240126305; Characters preserved in NFC; ASCII fallback used only for key/file generation.",
  "provisions": [],
  "provision_versions": [],
  "definitions": []
}
