{
  "id": "2024:1667",
  "type": "statute",
  "title": "Lov om ændring af selskabsloven (Offentligt udbud af anparter og nedsættelse af minimumskrav til anpartsselskabers selskabskapital)",
  "short_name": "LOV Æ#LOKDOK02",
  "status": "in_force",
  "issued_date": "2024-12-30",
  "url": "https://www.retsinformation.dk/eli/lta/2024/1667/xml",
  "description": "Retsinformation source. DocumentId=CQ003108; AccessionNumber=A20240166730; Characters preserved in NFC; ASCII fallback used only for key/file generation.",
  "provisions": [],
  "provision_versions": [],
  "definitions": []
}
